[
  {
    "id": 1768362020333617,
    "song_title": "Te Levar Daqui",
    "year": 1999,
    "artist_name": "Charlie Brown Jr.",
    "artist_genre": "Live",
    "youtube_link": "https://www.youtube.com/watch?v=sWsedr5pQVc"
  },
  {
    "id": 1768362020333620,
    "song_title": "12+1 (Doze Mais Um)",
    "year": 1999,
    "artist_name": "Charlie Brown Jr.",
    "artist_genre": "Live",
    "youtube_link": "https://www.youtube.com/watch?v=OCy5T-l3kSM"
  },
  {
    "id": 1768362020333628,
    "song_title": "Cruzei Uma Doida",
    "year": 1999,
    "artist_name": "Charlie Brown Jr.",
    "artist_genre": "Live",
    "youtube_link": "https://www.youtube.com/watch?v=_sJn7wuJWfc"
  },
  {
    "id": 1768362020333719,
    "song_title": "Confisco",
    "year": 1999,
    "artist_name": "Charlie Brown Jr.",
    "artist_genre": "Live",
    "youtube_link": "https://www.youtube.com/watch?v=yT5-UXD4oy4"
  },
  {
    "id": 1768362020333752,
    "song_title": "Não Deixe O Mar Te Engolir",
    "year": 1999,
    "artist_name": "Charlie Brown Jr.",
    "artist_genre": "Live",
    "youtube_link": "https://www.youtube.com/watch?v=iQYWlARufIM"
  },
  {
    "id": 1768362020333754,
    "song_title": "Uniao",
    "year": 1999,
    "artist_name": "Charlie Brown Jr.",
    "artist_genre": "Live",
    "youtube_link": "https://www.youtube.com/watch?v=hSR0mtPrngE"
  },
  {
    "id": 1768362020333754,
    "song_title": "Do Surf",
    "year": 1999,
    "artist_name": "Charlie Brown Jr.",
    "artist_genre": "Live",
    "youtube_link": "https://www.youtube.com/watch?v=MyojWkfDHvQ"
  },
  {
    "id": 1768362020333760,
    "song_title": "Confisco",
    "year": 1999,
    "artist_name": "Charlie Brown Jr.",
    "artist_genre": "Live",
    "youtube_link": "https://www.youtube.com/watch?v=Umf3cAxLrEk"
  },
  {
    "id": 1768362020333774,
    "song_title": "Te Levar Daqui",
    "year": 1999,
    "artist_name": "Charlie Brown Jr.",
    "artist_genre": "Live",
    "youtube_link": "https://www.youtube.com/watch?v=EA9AwIUiYgs"
  },
  {
    "id": 1768362020333778,
    "song_title": "Não Deixe O Mar Te Engolir",
    "year": 1999,
    "artist_name": "Charlie Brown Jr.",
    "artist_genre": "Rock",
    "youtube_link": "https://www.youtube.com/watch?v=2RobhjC7cR4"
  },
  {
    "id": 533173701873,
    "song_title": "Ta Tudo Bem",
    "year": 1999,
    "artist_genre": "Pop",
    "youtube_link": "https://www.youtube.com/watch?v=0qH56Z59rBE",
    "imvdb_url": "https://imvdb.com/video/ivete-sangalo/ta-tudo-bem",
    "artist": "Ivete Sangalo"
  },
  {
    "id": "yt_qSoxNHUBfkk",
    "song_title": "Nada",
    "year": 1999,
    "artist_name": "Olho Seco",
    "artist_genre": "Live",
    "youtube_link": "https://www.youtube.com/watch?v=qSoxNHUBfkk",
    "imvdb_url": null,
    "source": "YouTube"
  }
]