[
  {
    "id": 297687966795,
    "song_title": "Cobertor",
    "year": 2014,
    "artist_genre": "Pop",
    "youtube_link": "https://www.youtube.com/watch?v=sMUVXJId8Eo",
    "imvdb_url": "https://imvdb.com/video/anitta/cobertor",
    "artist": "Anitta"
  },
  {
    "id": 208063659040,
    "song_title": "Setevidas",
    "year": 2014,
    "artist_genre": "Rock",
    "youtube_link": "https://www.youtube.com/watch?v=6qpV_KiB3Gg",
    "imvdb_url": "https://imvdb.com/video/pitty/setevidas",
    "artist": "Pitty"
  },
  {
    "id": 128645312957,
    "song_title": "Fardado",
    "year": 2014,
    "artist_genre": "Rock Alternativo",
    "youtube_link": "https://www.youtube.com/watch?v=vt62Nc1hr2Q",
    "imvdb_url": "https://imvdb.com/video/titãs/fardado",
    "artist": "Titãs"
  },
  {
    "id": 860320543062,
    "song_title": "Serpente",
    "year": 2014,
    "artist_genre": "Rock",
    "youtube_link": "https://www.youtube.com/watch?v=GQMBzNfj7mc",
    "imvdb_url": "https://imvdb.com/video/pitty/serpente",
    "artist": "Pitty"
  },
  {
    "id": 294000339063,
    "song_title": "Você e Eu",
    "year": 2014,
    "artist_genre": "Desconhecido",
    "youtube_link": "https://www.youtube.com/watch?v=NbLWfVxSs2I",
    "imvdb_url": "https://imvdb.com/video/gilberto-gil/voce-e-eu",
    "artist": "Gilberto Gil"
  },
  {
    "id": 993511674796,
    "song_title": "Na Batida",
    "year": 2014,
    "artist_genre": "Pop",
    "youtube_link": "https://www.youtube.com/watch?v=w1vNtmh1SqU",
    "imvdb_url": "https://imvdb.com/video/anitta/na-batida",
    "artist": "Anitta"
  },
  {
    "id": 107105598134,
    "song_title": "Te dar um beijo",
    "year": 2014,
    "artist_genre": "Desconhecido",
    "youtube_link": "https://www.youtube.com/watch?v=534F0cCssJI",
    "imvdb_url": "https://imvdb.com/video/michel-teló/te-dar-um-beijo",
    "artist": "Michel Teló"
  },
  {
    "id": 701532751728,
    "song_title": "Ritmo Perfeito",
    "year": 2014,
    "artist_genre": "Pop",
    "youtube_link": "https://www.youtube.com/watch?v=aMWa2DLEcIw",
    "imvdb_url": "https://imvdb.com/video/anitta/ritmo-perfeito",
    "artist": "Anitta"
  },
  {
    "id": 753438107200,
    "song_title": "Zen (Spanish Version)",
    "year": 2014,
    "artist_genre": [
      "Pop",
      "Latino"
    ],
    "youtube_link": "https://www.youtube.com/watch?v=HRp9rpUtfoY",
    "imvdb_url": "https://imvdb.com/video/anitta/zen-spanish-version",
    "artist": "Anitta"
  },
  {
    "id": 133628241570,
    "song_title": "No Meio da Torcida",
    "year": 2014,
    "artist_genre": "Pop",
    "youtube_link": "https://www.youtube.com/watch?v=cIiH6kiphaY",
    "imvdb_url": "https://imvdb.com/video/anitta/no-meio-da-torcida",
    "artist": "Anitta"
  },
  {
    "id": 947463426194,
    "song_title": "Duas De Cinco / Cóccix-ência",
    "year": 2014,
    "artist_genre": "Desconhecido",
    "youtube_link": "https://www.youtube.com/watch?v=MCtVS9wh26Y",
    "imvdb_url": "https://imvdb.com/video/criolo/duas-de-cinco-coccix-encia",
    "artist": "Criolo"
  },
  {
    "id": 139966146836,
    "song_title": "Meu Sol",
    "year": 2014,
    "artist_name": "Vanguart",
    "artist_genre": "Indie",
    "youtube_link": "https://www.youtube.com/watch?v=m-Tuvz2Iv3Y",
    "imvdb_url": "https://imvdb.com/video/vanguart/meu-sol",
    "source": "IMVDb"
  },
  {
    "id": "yt_r8-mF4l-07o",
    "song_title": "Angra - Time (Official)",
    "year": 2014,
    "artist_name": "Angra",
    "artist_genre": "Desconhecido",
    "youtube_link": "https://www.youtube.com/watch?v=r8-mF4l-07o",
    "imvdb_url": null,
    "source": "YouTube"
  },
  {
    "id": "yt_6b0Dn2mBaTs",
    "song_title": "Angra - Wishing Well (Official)",
    "year": 2014,
    "artist_name": "Angra",
    "artist_genre": "Desconhecido",
    "youtube_link": "https://www.youtube.com/watch?v=6b0Dn2mBaTs",
    "imvdb_url": null,
    "source": "YouTube"
  },
  {
    "id": "yt_j1kNmgaIY7M",
    "song_title": "Angra - Make Believe (Official)",
    "year": 2014,
    "artist_name": "Angra",
    "artist_genre": "Desconhecido",
    "youtube_link": "https://www.youtube.com/watch?v=j1kNmgaIY7M",
    "imvdb_url": null,
    "source": "YouTube"
  },
  {
    "id": "yt_NbJm6wX1fCw",
    "song_title": "Angra - Rebirth (Official)",
    "year": 2014,
    "artist_name": "Angra",
    "artist_genre": "Desconhecido",
    "youtube_link": "https://www.youtube.com/watch?v=NbJm6wX1fCw",
    "imvdb_url": null,
    "source": "YouTube"
  },
  {
    "id": "yt_LqaDmOLRhME",
    "song_title": "Angra - Carry On (Official)",
    "year": 2014,
    "artist_name": "Angra",
    "artist_genre": "Desconhecido",
    "youtube_link": "https://www.youtube.com/watch?v=LqaDmOLRhME",
    "imvdb_url": null,
    "source": "YouTube"
  },
  {
    "id": "yt_fHBKVJGSvQE",
    "song_title": "Antidemon - O que era ruim ficou Pior",
    "year": 2014,
    "artist_name": "Antidemon",
    "artist_genre": "Desconhecido",
    "youtube_link": "https://www.youtube.com/watch?v=fHBKVJGSvQE",
    "imvdb_url": null,
    "source": "YouTube"
  },
  {
    "id": "yt_lfbFpKLvMGk",
    "song_title": "Ao Cubo - 1980",
    "year": 2014,
    "artist_name": "Ao Cubo",
    "artist_genre": "Desconhecido",
    "youtube_link": "https://www.youtube.com/watch?v=lfbFpKLvMGk",
    "imvdb_url": null,
    "source": "YouTube"
  },
  {
    "id": "yt_JkK8g6FMEXE",
    "song_title": "Aerosmith - I Don't Want to Miss a Thing (Official HD Video)",
    "year": 2014,
    "artist_name": "Armagedom",
    "artist_genre": "Desconhecido",
    "youtube_link": "https://www.youtube.com/watch?v=JkK8g6FMEXE",
    "imvdb_url": null,
    "source": "YouTube"
  },
  {
    "id": "yt_Skj3JCUi3wc",
    "song_title": "Babado Novo - 15 Mil Por Mês",
    "year": 2014,
    "artist_name": "Babado Novo",
    "artist_genre": "Desconhecido",
    "youtube_link": "https://www.youtube.com/watch?v=Skj3JCUi3wc",
    "imvdb_url": null,
    "source": "YouTube"
  },
  {
    "id": "yt_C3fWm0xYic8",
    "song_title": "Canoeiro (Pescaria) - Bando da Lua (1949)",
    "year": 2014,
    "artist_name": "Bando da Lua",
    "artist_genre": "Desconhecido",
    "youtube_link": "https://www.youtube.com/watch?v=C3fWm0xYic8",
    "imvdb_url": null,
    "source": "YouTube"
  },
  {
    "id": "yt_G4VajXeWQAw",
    "song_title": "Antro de trastes",
    "year": 2014,
    "artist_name": "Blind Pigs",
    "artist_genre": "Punk",
    "youtube_link": "https://www.youtube.com/watch?v=G4VajXeWQAw",
    "imvdb_url": null,
    "source": "YouTube"
  },
  {
    "id": "yt_DkwG8Ax-YnY",
    "song_title": "Bonde da Stronda - Blindão feat. LetoDie",
    "year": 2014,
    "artist_name": "Bonde da Stronda",
    "artist_genre": "Desconhecido",
    "youtube_link": "https://www.youtube.com/watch?v=DkwG8Ax-YnY",
    "imvdb_url": null,
    "source": "YouTube"
  },
  {
    "id": "yt_VETYoF7VVf4",
    "song_title": "Bonde da Stronda - Na Atividade part. MC Guimê (Videoclipe Oficial)",
    "year": 2014,
    "artist_name": "Bonde da Stronda",
    "artist_genre": "Desconhecido",
    "youtube_link": "https://www.youtube.com/watch?v=VETYoF7VVf4",
    "imvdb_url": null,
    "source": "YouTube"
  },
  {
    "id": "yt_Sc4zAXr0kd0",
    "song_title": "Cachorro Grande - Que Loucura! (clipe oficial)",
    "year": 2014,
    "artist_name": "Cachorro Grande",
    "artist_genre": "Desconhecido",
    "youtube_link": "https://www.youtube.com/watch?v=Sc4zAXr0kd0",
    "imvdb_url": null,
    "source": "YouTube"
  },
  {
    "id": "yt_-rc8SqdVbX4",
    "song_title": "Cachorro Grande - Lunático (clipe oficial)",
    "year": 2014,
    "artist_name": "Cachorro Grande",
    "artist_genre": "Desconhecido",
    "youtube_link": "https://www.youtube.com/watch?v=-rc8SqdVbX4",
    "imvdb_url": null,
    "source": "YouTube"
  },
  {
    "id": "yt_tq7HaK9a2ew",
    "song_title": "Camila - De Venus (Cover Lyric) Elypse",
    "year": 2014,
    "artist_name": "Camisa de V\\'eanus",
    "artist_genre": "Desconhecido",
    "youtube_link": "https://www.youtube.com/watch?v=tq7HaK9a2ew",
    "imvdb_url": null,
    "source": "YouTube"
  },
  {
    "id": "yt_hA927UE9anY",
    "song_title": "Estações",
    "year": 2014,
    "artist_name": "Catedral",
    "artist_genre": "Rock",
    "youtube_link": "https://www.youtube.com/watch?v=hA927UE9anY",
    "imvdb_url": null,
    "source": "YouTube"
  },
  {
    "id": "yt_8CanWZMXsVc",
    "song_title": "Cheiro De Amor - Swing de Mainha (Ao Vivo)",
    "year": 2014,
    "artist_name": "Cheiro de Amor",
    "artist_genre": "Pop",
    "youtube_link": "https://www.youtube.com/watch?v=8CanWZMXsVc",
    "imvdb_url": null,
    "source": "YouTube"
  },
  {
    "id": "yt_zROzwijvOwo",
    "song_title": "Comunidade Ninjitsu   Detetive Clipe",
    "year": 2014,
    "artist_name": "Comunidade Nin-Jitsu",
    "artist_genre": "Rock",
    "youtube_link": "https://www.youtube.com/watch?v=zROzwijvOwo",
    "imvdb_url": null,
    "source": "YouTube"
  },
  {
    "id": "yt_fMOrDO56pkg",
    "song_title": "Melô do Analfabeto - Clipe Comunidade Nin-Jitsu",
    "year": 2014,
    "artist_name": "Comunidade Nin-Jitsu",
    "artist_genre": "Rock",
    "youtube_link": "https://www.youtube.com/watch?v=fMOrDO56pkg",
    "imvdb_url": null,
    "source": "YouTube"
  },
  {
    "id": "yt_UPRz-7sX_3I",
    "song_title": "AH! EU TO SEM ERVA - COMUNIDADE NIN-JITSU",
    "year": 2014,
    "artist_name": "Comunidade Nin-Jitsu",
    "artist_genre": "Rock",
    "youtube_link": "https://www.youtube.com/watch?v=UPRz-7sX_3I",
    "imvdb_url": null,
    "source": "YouTube"
  },
  {
    "id": "yt_1f7PkeCHqt4",
    "song_title": "Clima de Rodeio - Dallas Company",
    "year": 2014,
    "artist_name": "Dallas Country",
    "artist_genre": "Country",
    "youtube_link": "https://www.youtube.com/watch?v=1f7PkeCHqt4",
    "imvdb_url": null,
    "source": "YouTube"
  },
  {
    "id": "yt_HBbtjCKqrw0",
    "song_title": "Detonautas Roque Clube - Acredite No Seu Coração (Clipe Oficial)",
    "year": 2014,
    "artist_name": "Detonautas Roque Clube",
    "artist_genre": "Rock",
    "youtube_link": "https://www.youtube.com/watch?v=HBbtjCKqrw0",
    "imvdb_url": null,
    "source": "YouTube"
  },
  {
    "id": "yt_Rrfj4wHS-Oc",
    "song_title": "Fruto Sagrado - Não Quero Mais Acordar Assim (Clipe Oficial MK Music)",
    "year": 2014,
    "artist_name": "Fruto Sagrado",
    "artist_genre": "Rock",
    "youtube_link": "https://www.youtube.com/watch?v=Rrfj4wHS-Oc",
    "imvdb_url": null,
    "source": "YouTube"
  },
  {
    "id": "yt_8MksLBGRUpo",
    "song_title": "Fruto Sagrado - 🧐 O Que Na Verdade Somos (Clipe Oficial MK Music)",
    "year": 2014,
    "artist_name": "Fruto Sagrado",
    "artist_genre": "Rock",
    "youtube_link": "https://www.youtube.com/watch?v=8MksLBGRUpo",
    "imvdb_url": null,
    "source": "YouTube"
  },
  {
    "id": "yt_at6LGyPQagM",
    "song_title": "Jack Kerouac",
    "year": 2014,
    "artist_name": "Gang 90 e as Absurdettes",
    "artist_genre": "Rock",
    "youtube_link": "https://www.youtube.com/watch?v=at6LGyPQagM",
    "imvdb_url": null,
    "source": "YouTube"
  },
  {
    "id": "yt_mBDTt2zXK78",
    "song_title": "Românticos A Go-Go",
    "year": 2014,
    "artist_name": "Gang 90 e as Absurdettes",
    "artist_genre": "Rock",
    "youtube_link": "https://www.youtube.com/watch?v=mBDTt2zXK78",
    "imvdb_url": null,
    "source": "YouTube"
  },
  {
    "id": "yt_jqmJ0VUkzBE",
    "song_title": "Eu Já Sei",
    "year": 2014,
    "artist_name": "Garotos da Rua",
    "artist_genre": "Rock",
    "youtube_link": "https://www.youtube.com/watch?v=jqmJ0VUkzBE",
    "imvdb_url": null,
    "source": "YouTube"
  },
  {
    "id": "yt_bVwK0l2GVko",
    "song_title": "Glory Opera - Iara",
    "year": 2014,
    "artist_name": "Glory Opera",
    "artist_genre": "Metal",
    "youtube_link": "https://www.youtube.com/watch?v=bVwK0l2GVko",
    "imvdb_url": null,
    "source": "YouTube"
  },
  {
    "id": "yt_28sRXLPUfb8",
    "song_title": "Homens de Marte - A Um Passo do Universo - Live at The Hobby Shop",
    "year": 2014,
    "artist_name": "Homens de Marte",
    "artist_genre": "Rock",
    "youtube_link": "https://www.youtube.com/watch?v=28sRXLPUfb8",
    "imvdb_url": null,
    "source": "YouTube"
  },
  {
    "id": "yt_dkKea-QkZpI",
    "song_title": "Inimigos da HP - Só Que Não - (Clipe Oficial)",
    "year": 2014,
    "artist_name": "Inimigos da HP",
    "artist_genre": "Samba",
    "youtube_link": "https://www.youtube.com/watch?v=dkKea-QkZpI",
    "imvdb_url": null,
    "source": "YouTube"
  },
  {
    "id": "yt_Pg53xwolJOE",
    "song_title": "INUMANOS - EQUIPAMENTO PRECÁRIO ( SUPER RARO )",
    "year": 2014,
    "artist_name": "Inumanos",
    "artist_genre": "Rap",
    "youtube_link": "https://www.youtube.com/watch?v=Pg53xwolJOE",
    "imvdb_url": null,
    "source": "YouTube"
  },
  {
    "id": "yt_EDxJG7KYzfc",
    "song_title": "Joelho de Porco - São Paulo by Day (Trombadinhas)",
    "year": 2014,
    "artist_name": "Joelho de Porco",
    "artist_genre": "Rock",
    "youtube_link": "https://www.youtube.com/watch?v=EDxJG7KYzfc",
    "imvdb_url": null,
    "source": "YouTube"
  },
  {
    "id": "yt_H2wavLO8fgg",
    "song_title": "John Bala Jones - Todo cuidado",
    "year": 2014,
    "artist_name": "John Bala Jones",
    "artist_genre": "Pop Rock",
    "youtube_link": "https://www.youtube.com/watch?v=H2wavLO8fgg",
    "imvdb_url": null,
    "source": "YouTube"
  },
  {
    "id": "yt_TynFsTZlGDU",
    "song_title": "Jota Quest - Só Hoje (Clipe Oficial)",
    "year": 2014,
    "artist_name": "Jota Quest",
    "artist_genre": "Pop Rock",
    "youtube_link": "https://www.youtube.com/watch?v=TynFsTZlGDU",
    "imvdb_url": null,
    "source": "YouTube"
  },
  {
    "id": "yt_IUO-o_Bg8AY",
    "song_title": "Jota Quest - Dentro de um Abraço (Clipe Oficial)",
    "year": 2014,
    "artist_name": "Jota Quest",
    "artist_genre": "Pop Rock",
    "youtube_link": "https://www.youtube.com/watch?v=IUO-o_Bg8AY",
    "imvdb_url": null,
    "source": "YouTube"
  },
  {
    "id": "yt_MOOkKmYRAfw",
    "song_title": "KLB - Vão Passando os Minutos (Clipe Oficial)",
    "year": 2014,
    "artist_name": "KLB",
    "artist_genre": "Pop",
    "youtube_link": "https://www.youtube.com/watch?v=MOOkKmYRAfw",
    "imvdb_url": null,
    "source": "YouTube"
  },
  {
    "id": "yt_svGhw6mBvfQ",
    "song_title": "LS JACK - TARDE DEMAIS-  VIDEO CLIPE (HD)",
    "year": 2014,
    "artist_name": "LS Jack",
    "artist_genre": "Pop Rock",
    "youtube_link": "https://www.youtube.com/watch?v=svGhw6mBvfQ",
    "imvdb_url": null,
    "source": "YouTube"
  },
  {
    "id": "yt_o-5tadS761M",
    "song_title": "Macucos e Armandinho   TCHAU   Vídeo Clip Oficial",
    "year": 2014,
    "artist_name": "Macucos",
    "artist_genre": "Reggae",
    "youtube_link": "https://www.youtube.com/watch?v=o-5tadS761M",
    "imvdb_url": null,
    "source": "YouTube"
  },
  {
    "id": "yt_z4-lLhMLkbI",
    "song_title": "Aquarela Do Brasil",
    "year": 2014,
    "artist_name": "Made in Brazil",
    "artist_genre": "Rock",
    "youtube_link": "https://www.youtube.com/watch?v=z4-lLhMLkbI",
    "imvdb_url": null,
    "source": "YouTube"
  },
  {
    "id": "yt_MHbwPrYjISc",
    "song_title": "Maria Do Relento - Conhece O Mario - Boa Qualidade - Clipe Oficial",
    "year": 2014,
    "artist_name": "Maria do Relento",
    "artist_genre": "Rock",
    "youtube_link": "https://www.youtube.com/watch?v=MHbwPrYjISc",
    "imvdb_url": null,
    "source": "YouTube"
  },
  {
    "id": "yt_WqVYKZSPvy4",
    "song_title": "Maria do Relento - Amor Crazy",
    "year": 2014,
    "artist_name": "Maria do Relento",
    "artist_genre": "Rock",
    "youtube_link": "https://www.youtube.com/watch?v=WqVYKZSPvy4",
    "imvdb_url": null,
    "source": "YouTube"
  },
  {
    "id": "yt_NAkCibImIVs",
    "song_title": "Tecnicolor",
    "year": 2014,
    "artist_name": "Os Mutantes",
    "artist_genre": "Rock",
    "youtube_link": "https://www.youtube.com/watch?v=NAkCibImIVs",
    "imvdb_url": null,
    "source": "YouTube"
  },
  {
    "id": "yt_uMfBKWeyk5Q",
    "song_title": "Os Mutantes - Balada Do Louco (Ao Vivo)",
    "year": 2014,
    "artist_name": "Os Mutantes",
    "artist_genre": "Rock",
    "youtube_link": "https://www.youtube.com/watch?v=uMfBKWeyk5Q",
    "imvdb_url": null,
    "source": "YouTube"
  },
  {
    "id": "yt_P6-7IGNHgyk",
    "song_title": "Mzuri Sana- Rap de Raiz.",
    "year": 2014,
    "artist_name": "Mzuri Sana",
    "artist_genre": "Rap",
    "youtube_link": "https://www.youtube.com/watch?v=P6-7IGNHgyk",
    "imvdb_url": null,
    "source": "YouTube"
  },
  {
    "id": "yt_ulOepjVFoOk",
    "song_title": "Madame Saatan - Moira (Web Music Video)",
    "year": 2014,
    "artist_name": "Madame Saatan",
    "artist_genre": "Metal",
    "youtube_link": "https://www.youtube.com/watch?v=ulOepjVFoOk",
    "imvdb_url": null,
    "source": "YouTube"
  },
  {
    "id": "yt_tRmtL8yxcSA",
    "song_title": "Natiruts - Sorri, Sou Rei (Natiruts Acústico Ao Vivo no Rio de Janeiro)",
    "year": 2014,
    "artist_name": "Natiruts",
    "artist_genre": "Reggae",
    "youtube_link": "https://www.youtube.com/watch?v=tRmtL8yxcSA",
    "imvdb_url": null,
    "source": "YouTube"
  },
  {
    "id": "yt_i1Nm-MJ313w",
    "song_title": "Natiruts - Quero Ser Feliz Também (Natiruts Acústico Ao Vivo no Rio de Janeiro)",
    "year": 2014,
    "artist_name": "Natiruts",
    "artist_genre": "Reggae",
    "youtube_link": "https://www.youtube.com/watch?v=i1Nm-MJ313w",
    "imvdb_url": null,
    "source": "YouTube"
  },
  {
    "id": "yt_Z3E60Fc0b6o",
    "song_title": "Natiruts - Você Me Encantou Demais (Natiruts Acústico Ao Vivo no Rio de Janeiro)",
    "year": 2014,
    "artist_name": "Natiruts",
    "artist_genre": "Reggae",
    "youtube_link": "https://www.youtube.com/watch?v=Z3E60Fc0b6o",
    "imvdb_url": null,
    "source": "YouTube"
  },
  {
    "id": "yt_Tu4sXwpY6S0",
    "song_title": "Natiruts - Andei Só (Natiruts Acústico Ao Vivo no Rio de Janeiro)",
    "year": 2014,
    "artist_name": "Natiruts",
    "artist_genre": "Reggae",
    "youtube_link": "https://www.youtube.com/watch?v=Tu4sXwpY6S0",
    "imvdb_url": null,
    "source": "YouTube"
  },
  {
    "id": "yt_WrBznflRvB8",
    "song_title": "O Surto - A Cera (Pirou o Cabeção) [ Videoclipe Oficial ]",
    "year": 2014,
    "artist_name": "O Surto",
    "artist_genre": "Rock",
    "youtube_link": "https://www.youtube.com/watch?v=WrBznflRvB8",
    "imvdb_url": null,
    "source": "YouTube"
  },
  {
    "id": "yt_kZAUycYl2n0",
    "song_title": "O Surto - Litoral (Videoclipe Oficial)",
    "year": 2014,
    "artist_name": "O Surto",
    "artist_genre": "Rock",
    "youtube_link": "https://www.youtube.com/watch?v=kZAUycYl2n0",
    "imvdb_url": null,
    "source": "YouTube"
  },
  {
    "id": "yt_ZwLrAHUgygA",
    "song_title": "Oficina G3 - Sempre Mais (Clipe Oficial MK Music)",
    "year": 2014,
    "artist_name": "Oficina G3",
    "artist_genre": "Rock",
    "youtube_link": "https://www.youtube.com/watch?v=ZwLrAHUgygA",
    "imvdb_url": null,
    "source": "YouTube"
  },
  {
    "id": "yt_RPzIjRTNA6o",
    "song_title": "Olho Seco - Nada - Isto é olho seco",
    "year": 2014,
    "artist_name": "Olho Seco",
    "artist_genre": "Punk",
    "youtube_link": "https://www.youtube.com/watch?v=RPzIjRTNA6o",
    "imvdb_url": null,
    "source": "YouTube"
  },
  {
    "id": "yt_pOW-DZ08oNA",
    "song_title": "Banda Reflexus - Madagascar Olodum (Ao Vivo)",
    "year": 2014,
    "artist_name": "Olodum",
    "artist_genre": "Axé",
    "youtube_link": "https://www.youtube.com/watch?v=pOW-DZ08oNA",
    "imvdb_url": null,
    "source": "YouTube"
  },
  {
    "id": "yt_ZZmOVlCSCt8",
    "song_title": "Os Paralamas Do Sucesso - Aonde Quer Que Eu Vá",
    "year": 2014,
    "artist_name": "Paralamas do Sucesso",
    "artist_genre": "Rock",
    "youtube_link": "https://www.youtube.com/watch?v=ZZmOVlCSCt8",
    "imvdb_url": null,
    "source": "YouTube"
  },
  {
    "id": "yt_trFdRPqjwyk",
    "song_title": "Os Paralamas Do Sucesso - Lanterna Dos Afogados",
    "year": 2014,
    "artist_name": "Paralamas do Sucesso",
    "artist_genre": "Rock",
    "youtube_link": "https://www.youtube.com/watch?v=trFdRPqjwyk",
    "imvdb_url": null,
    "source": "YouTube"
  },
  {
    "id": "yt_r6esToXGQJM",
    "song_title": "Os Paralamas Do Sucesso - Alagados",
    "year": 2014,
    "artist_name": "Paralamas do Sucesso",
    "artist_genre": "Rock",
    "youtube_link": "https://www.youtube.com/watch?v=r6esToXGQJM",
    "imvdb_url": null,
    "source": "YouTube"
  },
  {
    "id": "yt_0qpiLccePSQ",
    "song_title": "Backstage - Garota da playboy (Official Music Video HD)",
    "year": 2014,
    "artist_name": "The Playboys",
    "artist_genre": "Rock",
    "youtube_link": "https://www.youtube.com/watch?v=0qpiLccePSQ",
    "imvdb_url": null,
    "source": "YouTube"
  },
  {
    "id": "yt_MNhdPijqGkI",
    "song_title": "Polegar - Sou Como Sou",
    "year": 2014,
    "artist_name": "Polegar",
    "artist_genre": "Pop",
    "youtube_link": "https://www.youtube.com/watch?v=MNhdPijqGkI",
    "imvdb_url": null,
    "source": "YouTube"
  },
  {
    "id": "yt_7Y25hxMtuiE",
    "song_title": "Quinteto Violado e Lenine - Leão do Norte",
    "year": 2014,
    "artist_name": "Quinteto Violado",
    "artist_genre": "Regional",
    "youtube_link": "https://www.youtube.com/watch?v=7Y25hxMtuiE",
    "imvdb_url": null,
    "source": "YouTube"
  },
  {
    "id": "yt_kab3hBdmVoo",
    "song_title": "O Rappa - O Que Sobrou do Céu (Clipe Oficial)",
    "year": 2014,
    "artist_name": "O Rappa",
    "artist_genre": "Rock",
    "youtube_link": "https://www.youtube.com/watch?v=kab3hBdmVoo",
    "imvdb_url": null,
    "source": "YouTube"
  },
  {
    "id": "yt_X9WU4NQMYCI",
    "song_title": "Como fazer uma Armadilha para Ratos",
    "year": 2014,
    "artist_name": "Ratos de Por\\'e3o",
    "artist_genre": "Desconhecido",
    "youtube_link": "https://www.youtube.com/watch?v=X9WU4NQMYCI",
    "imvdb_url": null,
    "source": "YouTube"
  },
  {
    "id": "yt_OtDvlKRgJrc",
    "song_title": "Renascer Praise - Jesus, O Plano Perfeito",
    "year": 2014,
    "artist_name": "Renascer Praise",
    "artist_genre": "Gospel",
    "youtube_link": "https://www.youtube.com/watch?v=OtDvlKRgJrc",
    "imvdb_url": null,
    "source": "YouTube"
  },
  {
    "id": "yt_QTC7_DVENZA",
    "song_title": "Renascer Praise - 1000 Graus",
    "year": 2014,
    "artist_name": "Renascer Praise",
    "artist_genre": "Gospel",
    "youtube_link": "https://www.youtube.com/watch?v=QTC7_DVENZA",
    "imvdb_url": null,
    "source": "YouTube"
  },
  {
    "id": "yt_ijTweJ1ZK1A",
    "song_title": "Renascer Praise - Andando Sobre as Águas (Ao Vivo)",
    "year": 2014,
    "artist_name": "Renascer Praise",
    "artist_genre": "Gospel",
    "youtube_link": "https://www.youtube.com/watch?v=ijTweJ1ZK1A",
    "imvdb_url": null,
    "source": "YouTube"
  },
  {
    "id": "yt_b_qi6nUKchw",
    "song_title": "Renascer Praise - Mil Graus",
    "year": 2014,
    "artist_name": "Renascer Praise",
    "artist_genre": "Gospel",
    "youtube_link": "https://www.youtube.com/watch?v=b_qi6nUKchw",
    "imvdb_url": null,
    "source": "YouTube"
  },
  {
    "id": "yt_4w8WEird-F0",
    "song_title": "Resgate - Infinitamente Mais",
    "year": 2014,
    "artist_name": "Resgate",
    "artist_genre": "Rock",
    "youtube_link": "https://www.youtube.com/watch?v=4w8WEird-F0",
    "imvdb_url": null,
    "source": "YouTube"
  },
  {
    "id": "yt_DaIgoy16eTo",
    "song_title": "Restart - Renascer (clipe Oficial HD)",
    "year": 2014,
    "artist_name": "Restart",
    "artist_genre": "Pop Rock",
    "youtube_link": "https://www.youtube.com/watch?v=DaIgoy16eTo",
    "imvdb_url": null,
    "source": "YouTube"
  },
  {
    "id": "yt_-iHnXoWCLAA",
    "song_title": "Rosa de Saron - Cartas ao Remetente (Vídeoclipe OFICIAL)",
    "year": 2014,
    "artist_name": "Rosa de Saron",
    "artist_genre": "Rock",
    "youtube_link": "https://www.youtube.com/watch?v=-iHnXoWCLAA",
    "imvdb_url": null,
    "source": "YouTube"
  },
  {
    "id": "yt_Ey_O48VB_fU",
    "song_title": "Roupa Nova - Dona (Ao Vivo)",
    "year": 2014,
    "artist_name": "Roupa Nova",
    "artist_genre": "Pop",
    "youtube_link": "https://www.youtube.com/watch?v=Ey_O48VB_fU",
    "imvdb_url": null,
    "source": "YouTube"
  },
  {
    "id": "yt_t-zb_hdU24o",
    "song_title": "Roupa Nova - A Viagem (Ao Vivo)",
    "year": 2014,
    "artist_name": "Roupa Nova",
    "artist_genre": "Pop",
    "youtube_link": "https://www.youtube.com/watch?v=t-zb_hdU24o",
    "imvdb_url": null,
    "source": "YouTube"
  },
  {
    "id": "yt_TYbhUbYK7fM",
    "song_title": "Roupa Nova - Chama (Vídeo Ao Vivo)",
    "year": 2014,
    "artist_name": "Roupa Nova",
    "artist_genre": "Pop",
    "youtube_link": "https://www.youtube.com/watch?v=TYbhUbYK7fM",
    "imvdb_url": null,
    "source": "YouTube"
  },
  {
    "id": "yt_GUVoVoQ1oRM",
    "song_title": "Roupa Nova - Linda Demais (Ao Vivo)",
    "year": 2014,
    "artist_name": "Roupa Nova",
    "artist_genre": "Pop",
    "youtube_link": "https://www.youtube.com/watch?v=GUVoVoQ1oRM",
    "imvdb_url": null,
    "source": "YouTube"
  },
  {
    "id": "yt_U1X98SRZnmc",
    "song_title": "Roupa Nova - Começo, Meio e Fim (Vídeo Ao Vivo)",
    "year": 2014,
    "artist_name": "Roupa Nova",
    "artist_genre": "Pop",
    "youtube_link": "https://www.youtube.com/watch?v=U1X98SRZnmc",
    "imvdb_url": null,
    "source": "YouTube"
  },
  {
    "id": "yt_wHa9ME0rIeg",
    "song_title": "Rumbora - Chapirous",
    "year": 2014,
    "artist_name": "Rumbora",
    "artist_genre": "Rock",
    "youtube_link": "https://www.youtube.com/watch?v=wHa9ME0rIeg",
    "imvdb_url": null,
    "source": "YouTube"
  },
  {
    "id": "yt_5sJxATIDheg",
    "song_title": "Amor - Secos & Molhados (1974)",
    "year": 2014,
    "artist_name": "Secos e Molhados",
    "artist_genre": "MPB",
    "youtube_link": "https://www.youtube.com/watch?v=5sJxATIDheg",
    "imvdb_url": null,
    "source": "YouTube"
  },
  {
    "id": "yt_pSkVHcF7qAo",
    "song_title": "Habitual",
    "year": 2014,
    "artist_name": "Shadowside",
    "artist_genre": "Metal",
    "youtube_link": "https://www.youtube.com/watch?v=pSkVHcF7qAo",
    "imvdb_url": null,
    "source": "YouTube"
  },
  {
    "id": "yt_IPqCbXRgKlU",
    "song_title": "Stauros - Conflitos Mortais (Vídeo Clipe)",
    "year": 2014,
    "artist_name": "Stauros",
    "artist_genre": "Metal",
    "youtube_link": "https://www.youtube.com/watch?v=IPqCbXRgKlU",
    "imvdb_url": null,
    "source": "YouTube"
  },
  {
    "id": "yt_umZsyAu3xik",
    "song_title": "Bote Fé!",
    "year": 2014,
    "artist_name": "Tihuana",
    "artist_genre": "Rock",
    "youtube_link": "https://www.youtube.com/watch?v=umZsyAu3xik",
    "imvdb_url": null,
    "source": "YouTube"
  },
  {
    "id": "yt_WiTzMYp5CeI",
    "song_title": "Jorge Ben Jor - Gostosa",
    "year": 2014,
    "artist_name": "Jorge Ben Jor",
    "artist_genre": "MPB",
    "youtube_link": "https://www.youtube.com/watch?v=WiTzMYp5CeI",
    "imvdb_url": null,
    "source": "YouTube"
  },
  {
    "id": "yt_UaQSLWJxIwc",
    "song_title": "Ese Tipo Soy Yo (Esse Cara Sou Eu) - Ao vivo em Las Vegas",
    "year": 2014,
    "artist_name": "Roberto Carlos",
    "artist_genre": [
      "MPB",
      "Latino"
    ],
    "youtube_link": "https://www.youtube.com/watch?v=UaQSLWJxIwc",
    "imvdb_url": null,
    "source": "YouTube"
  },
  {
    "id": "yt_DS6fRsfnzIw",
    "song_title": "A Triste Partida - Luiz Gonzaga",
    "year": 2014,
    "artist_name": "Luiz Gonzaga",
    "artist_genre": "Regional",
    "youtube_link": "https://www.youtube.com/watch?v=DS6fRsfnzIw",
    "imvdb_url": null,
    "source": "YouTube"
  },
  {
    "id": "yt_j44wrohm3ac",
    "song_title": "Da Lama ao Caos",
    "year": 2014,
    "artist_name": "Sepultura",
    "artist_genre": "Metal",
    "youtube_link": "https://www.youtube.com/watch?v=j44wrohm3ac",
    "imvdb_url": null,
    "source": "YouTube"
  },
  {
    "id": "yt_jb5z-_TyJfw",
    "song_title": "A casa - Vinicius de Moraes (videoclipe)",
    "year": 2014,
    "artist_name": "Vinicius de Moraes",
    "artist_genre": "MPB",
    "youtube_link": "https://www.youtube.com/watch?v=jb5z-_TyJfw",
    "imvdb_url": null,
    "source": "YouTube"
  },
  {
    "id": "yt_8Rd1qKX-KxU",
    "song_title": "Arnaldo Baptista - Vou Me Afundar Na Lingerie",
    "year": 2014,
    "artist_name": "Arnaldo Baptista",
    "artist_genre": "Desconhecido",
    "youtube_link": "https://www.youtube.com/watch?v=8Rd1qKX-KxU",
    "imvdb_url": null,
    "source": "YouTube"
  },
  {
    "id": "yt_eqkPZcQJ16U",
    "song_title": "Heitor Villa-Lobos play Villa-Lobos (Video)",
    "year": 2014,
    "artist_name": "Heitor Villa-Lobos",
    "artist_genre": "Clássico",
    "youtube_link": "https://www.youtube.com/watch?v=eqkPZcQJ16U",
    "imvdb_url": null,
    "source": "YouTube"
  },
  {
    "id": "yt_q-D9zyJXznI",
    "song_title": "Baden Powell - Valsa Sem Nome",
    "year": 2014,
    "artist_name": "Baden Powell",
    "artist_genre": "Desconhecido",
    "youtube_link": "https://www.youtube.com/watch?v=q-D9zyJXznI",
    "imvdb_url": null,
    "source": "YouTube"
  },
  {
    "id": "yt_DTgdkFjXSM0",
    "song_title": "Mano Brown canta Vida Loka I",
    "year": 2014,
    "artist_name": "Mano Brown",
    "artist_genre": "Rap",
    "youtube_link": "https://www.youtube.com/watch?v=DTgdkFjXSM0",
    "imvdb_url": null,
    "source": "YouTube"
  },
  {
    "id": "yt_V6T07WuDSOI",
    "song_title": "Mano Brown - \"Boa Noite SP\" (Ao Vivo no SP Rap 2014)",
    "year": 2014,
    "artist_name": "Mano Brown",
    "artist_genre": "Rap",
    "youtube_link": "https://www.youtube.com/watch?v=V6T07WuDSOI",
    "imvdb_url": null,
    "source": "YouTube"
  },
  {
    "id": 514358037606,
    "song_title": "Ex-Quadrilha Da Fumaça",
    "year": 2014,
    "artist_name": "Planet Hemp",
    "artist_genre": "Rap",
    "youtube_link": "https://www.youtube.com/watch?v=GGnyoknc980"
  }
]