[
  {
    "id": 137264714961,
    "song_title": "Triste com T",
    "year": 2021,
    "artist_genre": "Desconhecido",
    "youtube_link": "https://www.youtube.com/watch?v=_K7WVDfOEYY",
    "imvdb_url": "https://imvdb.com/video/pabllo-vittar/triste-com-t",
    "artist": "Pabllo Vittar"
  },
  {
    "id": 317760064185,
    "song_title": "Nothing Ever Hurt Like You",
    "year": 2021,
    "artist_name": "LEELA",
    "artist_genre": "Rock",
    "youtube_link": "https://www.youtube.com/watch?v=X3_eQh0BPHw",
    "imvdb_url": "https://imvdb.com/video/leela/nothing-ever-hurt-like-you",
    "source": "IMVDb"
  },
  {
    "id": "yt_1xILbb5RREI",
    "song_title": "A Bolha",
    "year": 2021,
    "artist_name": "A Bolha",
    "artist_genre": "Desconhecido",
    "youtube_link": "https://www.youtube.com/watch?v=1xILbb5RREI",
    "imvdb_url": null,
    "source": "YouTube"
  },
  {
    "id": "yt_3ZnBpxR2dQs",
    "song_title": "Abbot - Ando Negro",
    "year": 2021,
    "artist_name": "Ado Negro",
    "artist_genre": "Desconhecido",
    "youtube_link": "https://www.youtube.com/watch?v=3ZnBpxR2dQs",
    "imvdb_url": null,
    "source": "YouTube"
  },
  {
    "id": "yt_dIFzUVxAb8c",
    "song_title": "Povoada - Sued Nunes",
    "year": 2021,
    "artist_name": "Ado Negro",
    "artist_genre": "Desconhecido",
    "youtube_link": "https://www.youtube.com/watch?v=dIFzUVxAb8c",
    "imvdb_url": null,
    "source": "YouTube"
  },
  {
    "id": "yt_4kzxy8eIjLI",
    "song_title": "AMONG US 🎵 Minecraft Animation Music Video [VERSION A] (“Lyin’ To Me” Song by CG5)",
    "year": 2021,
    "artist_name": "Almandegas",
    "artist_genre": "Desconhecido",
    "youtube_link": "https://www.youtube.com/watch?v=4kzxy8eIjLI",
    "imvdb_url": null,
    "source": "YouTube"
  },
  {
    "id": "yt_kUPypjnRt8A",
    "song_title": "ARION Ft. CYAN KICKS - In The Name Of Love - (2021) // Official Music Video // AFM Records",
    "year": 2021,
    "artist_name": "Arion",
    "artist_genre": "Desconhecido",
    "youtube_link": "https://www.youtube.com/watch?v=kUPypjnRt8A",
    "imvdb_url": null,
    "source": "YouTube"
  },
  {
    "id": "yt_ygno4cGrO4A",
    "song_title": "ARION - Out Of My Life (2021) // Official Music Video // AFM Records",
    "year": 2021,
    "artist_name": "Arion",
    "artist_genre": "Desconhecido",
    "youtube_link": "https://www.youtube.com/watch?v=ygno4cGrO4A",
    "imvdb_url": null,
    "source": "YouTube"
  },
  {
    "id": "yt_K17df81RL9Y",
    "song_title": "AURORA - Cure For Me",
    "year": 2021,
    "artist_name": "Autoras",
    "artist_genre": "Desconhecido",
    "youtube_link": "https://www.youtube.com/watch?v=K17df81RL9Y",
    "imvdb_url": null,
    "source": "YouTube"
  },
  {
    "id": "yt_sJZ1G0e5bWU",
    "song_title": "Lio - Le Banana Split (Clip Officiel)",
    "year": 2021,
    "artist_name": "Banana Split",
    "artist_genre": "Desconhecido",
    "youtube_link": "https://www.youtube.com/watch?v=sJZ1G0e5bWU",
    "imvdb_url": null,
    "source": "YouTube"
  },
  {
    "id": "yt_0h86S5fN9pQ",
    "song_title": "THE DICKIES - Banana Splits (Promo 1979) best quality",
    "year": 2021,
    "artist_name": "Banana Split",
    "artist_genre": "Desconhecido",
    "youtube_link": "https://www.youtube.com/watch?v=0h86S5fN9pQ",
    "imvdb_url": null,
    "source": "YouTube"
  },
  {
    "id": "yt_iO2Iwczncw0",
    "song_title": "Banda De Pau E Corda - Flor D'Agua (Áudio Oficial)",
    "year": 2021,
    "artist_name": "Banda de Pau e Corda",
    "artist_genre": "Desconhecido",
    "youtube_link": "https://www.youtube.com/watch?v=iO2Iwczncw0",
    "imvdb_url": null,
    "source": "YouTube"
  },
  {
    "id": "yt_ngMqrlnZ-0k",
    "song_title": "Banda De Pau E Corda - Mestre Mundo (Áudio Oficial)",
    "year": 2021,
    "artist_name": "Banda de Pau e Corda",
    "artist_genre": "Desconhecido",
    "youtube_link": "https://www.youtube.com/watch?v=ngMqrlnZ-0k",
    "imvdb_url": null,
    "source": "YouTube"
  },
  {
    "id": "yt_bqdlugU1X80",
    "song_title": "Banda De Pau E Corda - Caminhada (Áudio Oficial)",
    "year": 2021,
    "artist_name": "Banda de Pau e Corda",
    "artist_genre": "Desconhecido",
    "youtube_link": "https://www.youtube.com/watch?v=bqdlugU1X80",
    "imvdb_url": null,
    "source": "YouTube"
  },
  {
    "id": "yt_HjX6IJ5XsF4",
    "song_title": "Banda De Pau E Corda - Esperança (Áudio Oficial)",
    "year": 2021,
    "artist_name": "Banda de Pau e Corda",
    "artist_genre": "Desconhecido",
    "youtube_link": "https://www.youtube.com/watch?v=HjX6IJ5XsF4",
    "imvdb_url": null,
    "source": "YouTube"
  },
  {
    "id": "yt_dl_cDLA6RuE",
    "song_title": "Banda De Pau E Corda - Vivência (Áudio Oficial)",
    "year": 2021,
    "artist_name": "Banda de Pau e Corda",
    "artist_genre": "Desconhecido",
    "youtube_link": "https://www.youtube.com/watch?v=dl_cDLA6RuE",
    "imvdb_url": null,
    "source": "YouTube"
  },
  {
    "id": "yt_0q1W9edRhoY",
    "song_title": "Banda De Pau E Corda - Desafio (Áudio Oficial)",
    "year": 2021,
    "artist_name": "Banda de Pau e Corda",
    "artist_genre": "Desconhecido",
    "youtube_link": "https://www.youtube.com/watch?v=0q1W9edRhoY",
    "imvdb_url": null,
    "source": "YouTube"
  },
  {
    "id": "yt_-b1cIsPBZzI",
    "song_title": "O Outro Bando da Lua - Desarvorado",
    "year": 2021,
    "artist_name": "Bando da Lua",
    "artist_genre": "Desconhecido",
    "youtube_link": "https://www.youtube.com/watch?v=-b1cIsPBZzI",
    "imvdb_url": null,
    "source": "YouTube"
  },
  {
    "id": "yt_Z7Co2DqkaWY",
    "song_title": "\"In The Mood\" Brazil = Aloysio e seu Bando da lua (\"Edmundo\") song in movie \"Sun Valley Serenade\"",
    "year": 2021,
    "artist_name": "Bando da Lua",
    "artist_genre": "Desconhecido",
    "youtube_link": "https://www.youtube.com/watch?v=Z7Co2DqkaWY",
    "imvdb_url": null,
    "source": "YouTube"
  },
  {
    "id": "yt_GlkAWrFOPH8",
    "song_title": "Boca Livre, Marcelo Mariano - Bicicleta (Ao Vivo Em São Paulo / 2007)",
    "year": 2021,
    "artist_name": "Boca Livre",
    "artist_genre": "Desconhecido",
    "youtube_link": "https://www.youtube.com/watch?v=GlkAWrFOPH8",
    "imvdb_url": null,
    "source": "YouTube"
  },
  {
    "id": "yt_1jUPQ0p5v1k",
    "song_title": "Boca Livre, Rodrigo Maranhão - Feito Mistério (Ao Vivo Em São Paulo / 2007)",
    "year": 2021,
    "artist_name": "Boca Livre",
    "artist_genre": "Desconhecido",
    "youtube_link": "https://www.youtube.com/watch?v=1jUPQ0p5v1k",
    "imvdb_url": null,
    "source": "YouTube"
  },
  {
    "id": "yt_ZunTl8gnblY",
    "song_title": "Br'oz - Prometida (Videoclipe Oficial)",
    "year": 2021,
    "artist_name": "Br'oz",
    "artist_genre": "Desconhecido",
    "youtube_link": "https://www.youtube.com/watch?v=ZunTl8gnblY",
    "imvdb_url": null,
    "source": "YouTube"
  },
  {
    "id": "yt_TZ2m1eixsYc",
    "song_title": "Br'oz - Insana (Videoclipe Oficial)",
    "year": 2021,
    "artist_name": "Br'oz",
    "artist_genre": "Desconhecido",
    "youtube_link": "https://www.youtube.com/watch?v=TZ2m1eixsYc",
    "imvdb_url": null,
    "source": "YouTube"
  },
  {
    "id": "yt_56mu8KSUYqk",
    "song_title": "Cartola - Preciso Me Encontrar (Áudio Oficial)",
    "year": 2021,
    "artist_name": "Cartolas",
    "artist_genre": "Rock",
    "youtube_link": "https://www.youtube.com/watch?v=56mu8KSUYqk",
    "imvdb_url": null,
    "source": "YouTube"
  },
  {
    "id": "yt_qIGN9fDhrEU",
    "song_title": "Cartola - O Sol Nascerá (Programa Ensaio)",
    "year": 2021,
    "artist_name": "Cartolas",
    "artist_genre": "Rock",
    "youtube_link": "https://www.youtube.com/watch?v=qIGN9fDhrEU",
    "imvdb_url": null,
    "source": "YouTube"
  },
  {
    "id": "yt_0_YWjMezuow",
    "song_title": "Cartola - Amor Proibido",
    "year": 2021,
    "artist_name": "Cartolas",
    "artist_genre": "Rock",
    "youtube_link": "https://www.youtube.com/watch?v=0_YWjMezuow",
    "imvdb_url": null,
    "source": "YouTube"
  },
  {
    "id": "yt_Xd0xM7pulo0",
    "song_title": "Cartola - Bem Feito",
    "year": 2021,
    "artist_name": "Cartolas",
    "artist_genre": "Rock",
    "youtube_link": "https://www.youtube.com/watch?v=Xd0xM7pulo0",
    "imvdb_url": null,
    "source": "YouTube"
  },
  {
    "id": "yt_xloJrlwCLFo",
    "song_title": "MORENA - Casaca (Videoclipe Oficial)",
    "year": 2021,
    "artist_name": "Casaca",
    "artist_genre": "Reggae",
    "youtube_link": "https://www.youtube.com/watch?v=xloJrlwCLFo",
    "imvdb_url": null,
    "source": "YouTube"
  },
  {
    "id": "yt_7OmHbFnxn2M",
    "song_title": "Casaca feat. Maskavo - Do Teu Jeito",
    "year": 2021,
    "artist_name": "Casaca",
    "artist_genre": "Reggae",
    "youtube_link": "https://www.youtube.com/watch?v=7OmHbFnxn2M",
    "imvdb_url": null,
    "source": "YouTube"
  },
  {
    "id": "yt_Q1HqO9j14WE",
    "song_title": "Maria Bethânia - Cheiro De Amor.",
    "year": 2021,
    "artist_name": "Cheiro de Amor",
    "artist_genre": "Pop",
    "youtube_link": "https://www.youtube.com/watch?v=Q1HqO9j14WE",
    "imvdb_url": null,
    "source": "YouTube"
  },
  {
    "id": "yt_Kjj1VguaJlw",
    "song_title": "The Clevers (Os Incríveis) - Unchained Melody (1964)",
    "year": 2021,
    "artist_name": "The Clevers",
    "artist_genre": "Rock",
    "youtube_link": "https://www.youtube.com/watch?v=Kjj1VguaJlw",
    "imvdb_url": null,
    "source": "YouTube"
  },
  {
    "id": "yt_23vmskMnpFI",
    "song_title": "Companhia do Calypso Ao Vivo em Goiânia • Show do 2º DVD com Mylla Karvalho e Lenne Bandeira (2006)",
    "year": 2021,
    "artist_name": "Companhia do Calypso",
    "artist_genre": "Pop",
    "youtube_link": "https://www.youtube.com/watch?v=23vmskMnpFI",
    "imvdb_url": null,
    "source": "YouTube"
  },
  {
    "id": "yt_U1BFoc-BrOI",
    "song_title": "DEFENSOR - LYRIC VIDEO - RAQUEL EMERICK",
    "year": 2021,
    "artist_name": "Defensores",
    "artist_genre": "Rock",
    "youtube_link": "https://www.youtube.com/watch?v=U1BFoc-BrOI",
    "imvdb_url": null,
    "source": "YouTube"
  },
  {
    "id": "yt_PooFx8wfHxs",
    "song_title": "DELARUE - ZONA BARRIAL (PROD ICEMOON MUSIC)",
    "year": 2021,
    "artist_name": "De La Rue",
    "artist_genre": "Rap",
    "youtube_link": "https://www.youtube.com/watch?v=PooFx8wfHxs",
    "imvdb_url": null,
    "source": "YouTube"
  },
  {
    "id": "yt_2A6TpvnmygM",
    "song_title": "DELARUE - COCODRILO TIBURON (OFFICIAL VIDEO)",
    "year": 2021,
    "artist_name": "De La Rue",
    "artist_genre": "Rap",
    "youtube_link": "https://www.youtube.com/watch?v=2A6TpvnmygM",
    "imvdb_url": null,
    "source": "YouTube"
  },
  {
    "id": "yt_GQbLKgtm2yU",
    "song_title": "DELARUE - MENTE PIRATA (OFFICIAL VIDEO)",
    "year": 2021,
    "artist_name": "De La Rue",
    "artist_genre": "Rap",
    "youtube_link": "https://www.youtube.com/watch?v=GQbLKgtm2yU",
    "imvdb_url": null,
    "source": "YouTube"
  },
  {
    "id": "yt_AFBm7kj8qrc",
    "song_title": "Diante do Trono - Sobre as Ruínas (Ao Vivo)",
    "year": 2021,
    "artist_name": "Diante do Trono",
    "artist_genre": "Gospel",
    "youtube_link": "https://www.youtube.com/watch?v=AFBm7kj8qrc",
    "imvdb_url": null,
    "source": "YouTube"
  },
  {
    "id": "yt_csTS97dSRY4",
    "song_title": "DVD Preciso de Ti - Diante do Trono 4 - (2001) HD",
    "year": 2021,
    "artist_name": "Diante do Trono",
    "artist_genre": "Gospel",
    "youtube_link": "https://www.youtube.com/watch?v=csTS97dSRY4",
    "imvdb_url": null,
    "source": "YouTube"
  },
  {
    "id": "yt_23JSnrbKkiU",
    "song_title": "Dibob - Só Alegria (videoclipe oficial)",
    "year": 2021,
    "artist_name": "Dibob",
    "artist_genre": "Pop Punk",
    "youtube_link": "https://www.youtube.com/watch?v=23JSnrbKkiU",
    "imvdb_url": null,
    "source": "YouTube"
  },
  {
    "id": "yt_q6IPDm6kFws",
    "song_title": "DR. SIN - 27 (Official Video)",
    "year": 2021,
    "artist_name": "Dr. Sin",
    "artist_genre": "Metal",
    "youtube_link": "https://www.youtube.com/watch?v=q6IPDm6kFws",
    "imvdb_url": null,
    "source": "YouTube"
  },
  {
    "id": "yt_FB7OBb5uSec",
    "song_title": "ETERNA  - NABRISA (CLIPE OFICIAL)",
    "year": 2021,
    "artist_name": "Eterna",
    "artist_genre": "Metal",
    "youtube_link": "https://www.youtube.com/watch?v=FB7OBb5uSec",
    "imvdb_url": null,
    "source": "YouTube"
  },
  {
    "id": "yt_REryc1TpeY8",
    "song_title": "Peggy Lee - Fever (Official Video)",
    "year": 2021,
    "artist_name": "The Fevers",
    "artist_genre": "Rock",
    "youtube_link": "https://www.youtube.com/watch?v=REryc1TpeY8",
    "imvdb_url": null,
    "source": "YouTube"
  },
  {
    "id": "yt_H_-x7zTSaYo",
    "song_title": "Armadilha",
    "year": 2021,
    "artist_name": "Finis Africae",
    "artist_genre": "Rock",
    "youtube_link": "https://www.youtube.com/watch?v=H_-x7zTSaYo",
    "imvdb_url": null,
    "source": "YouTube"
  },
  {
    "id": "yt_GaYrgeI5VZo",
    "song_title": "FINIS AFRICAE - ARMADILHA REMASTERIZADA (PRESENTE DOS FÃS)",
    "year": 2021,
    "artist_name": "Finis Africae",
    "artist_genre": "Rock",
    "youtube_link": "https://www.youtube.com/watch?v=GaYrgeI5VZo",
    "imvdb_url": null,
    "source": "YouTube"
  },
  {
    "id": "yt_lILv_fGDjTw",
    "song_title": "First And Forever - Let This Love Lie Dead (Official Music Video)",
    "year": 2021,
    "artist_name": "Fist",
    "artist_genre": "Metal",
    "youtube_link": "https://www.youtube.com/watch?v=lILv_fGDjTw",
    "imvdb_url": null,
    "source": "YouTube"
  },
  {
    "id": "yt_IF8jMmosMwk",
    "song_title": "Garotos de Ouro - Gaitita - 4ª Coxilha Nativista",
    "year": 2021,
    "artist_name": "Garotos de Ouro",
    "artist_genre": "Regional",
    "youtube_link": "https://www.youtube.com/watch?v=IF8jMmosMwk",
    "imvdb_url": null,
    "source": "YouTube"
  },
  {
    "id": "yt_fN-TAR0j7RU",
    "song_title": "DVD A História Viva da Música Gaúcha - Medley Garotos de Ouro",
    "year": 2021,
    "artist_name": "Garotos de Ouro",
    "artist_genre": "Regional",
    "youtube_link": "https://www.youtube.com/watch?v=fN-TAR0j7RU",
    "imvdb_url": null,
    "source": "YouTube"
  },
  {
    "id": "yt_RfPATvJgr7s",
    "song_title": "A Internacional - Garotos Podres",
    "year": 2021,
    "artist_name": "Garotos Podres",
    "artist_genre": "Punk",
    "youtube_link": "https://www.youtube.com/watch?v=RfPATvJgr7s",
    "imvdb_url": null,
    "source": "YouTube"
  },
  {
    "id": "yt_a-dB3V4yyJ8",
    "song_title": "Boy Golden - KD and Lunch Meat [Official Video]",
    "year": 2021,
    "artist_name": "Golden Boys",
    "artist_genre": "Pop",
    "youtube_link": "https://www.youtube.com/watch?v=a-dB3V4yyJ8",
    "imvdb_url": null,
    "source": "YouTube"
  },
  {
    "id": "yt_gGfK1EIT2bM",
    "song_title": "Wacotron - Gram And A Hoodie [Prod. Southside x Pyrex 808 MAFIA] (Official Music Video)",
    "year": 2021,
    "artist_name": "Gram",
    "artist_genre": "Indie",
    "youtube_link": "https://www.youtube.com/watch?v=gGfK1EIT2bM",
    "imvdb_url": null,
    "source": "YouTube"
  },
  {
    "id": "yt_HjJDZ4Sbo38",
    "song_title": "THA JUICEMAN ft. LOU GRAM (Official Music Video)",
    "year": 2021,
    "artist_name": "Gram",
    "artist_genre": "Indie",
    "youtube_link": "https://www.youtube.com/watch?v=HjJDZ4Sbo38",
    "imvdb_url": null,
    "source": "YouTube"
  },
  {
    "id": "yt_6hqsSJZClr0",
    "song_title": "Que bom é ter Jesus - Grupo Elo ( Fotos / jayrinho)",
    "year": 2021,
    "artist_name": "Grupo Elo",
    "artist_genre": "Gospel",
    "youtube_link": "https://www.youtube.com/watch?v=6hqsSJZClr0",
    "imvdb_url": null,
    "source": "YouTube"
  },
  {
    "id": "yt_I-zOCm9q7sQ",
    "song_title": "Grandes Louvores do Grupo Logos.",
    "year": 2021,
    "artist_name": "Grupo Logos",
    "artist_genre": "Gospel",
    "youtube_link": "https://www.youtube.com/watch?v=I-zOCm9q7sQ",
    "imvdb_url": null,
    "source": "YouTube"
  },
  {
    "id": "yt_CR-lTsdMlJk",
    "song_title": "Nas Hori x LOWC8 x KIID HORI x Wani Hori - DRIPT OUT (Music Video)",
    "year": 2021,
    "artist_name": "Hori",
    "artist_genre": "Pop Rock",
    "youtube_link": "https://www.youtube.com/watch?v=CR-lTsdMlJk",
    "imvdb_url": null,
    "source": "YouTube"
  },
  {
    "id": "yt_rJxWcn5Ud7A",
    "song_title": "Paulinho Moska e Inimigos do Rei - Zoombido - Uma barata chamada Kafka",
    "year": 2021,
    "artist_name": "Inimigos do Rei",
    "artist_genre": "Pop Rock",
    "youtube_link": "https://www.youtube.com/watch?v=rJxWcn5Ud7A",
    "imvdb_url": null,
    "source": "YouTube"
  },
  {
    "id": "yt_r9O65oqyUGY",
    "song_title": "Seja o Lider",
    "year": 2021,
    "artist_name": "Inumanos",
    "artist_genre": "Rap",
    "youtube_link": "https://www.youtube.com/watch?v=r9O65oqyUGY",
    "imvdb_url": null,
    "source": "YouTube"
  },
  {
    "id": "yt_Hvnjz-d4FOM",
    "song_title": "Katsbarnea - Amargo ou Doce (vídeo oficial)",
    "year": 2021,
    "artist_name": "Katsbarnea",
    "artist_genre": "Rock",
    "youtube_link": "https://www.youtube.com/watch?v=Hvnjz-d4FOM",
    "imvdb_url": null,
    "source": "YouTube"
  },
  {
    "id": "yt_1prk4vq-80c",
    "song_title": "Katsbarnea - A Torre de Babel (vídeo oficial)",
    "year": 2021,
    "artist_name": "Katsbarnea",
    "artist_genre": "Rock",
    "youtube_link": "https://www.youtube.com/watch?v=1prk4vq-80c",
    "imvdb_url": null,
    "source": "YouTube"
  },
  {
    "id": "yt_hJCZet2PMKw",
    "song_title": "E-40 \"I STAND ON THAT\" FT. JOYNER LUCAS & T.I. (MUSIC VIDEO)",
    "year": 2021,
    "artist_name": "Legi\\'e3o Urbana",
    "artist_genre": "Desconhecido",
    "youtube_link": "https://www.youtube.com/watch?v=hJCZet2PMKw",
    "imvdb_url": null,
    "source": "YouTube"
  },
  {
    "id": "yt_PweyXXYvS6o",
    "song_title": "Ludovico Technique - Embrace (Official Music Video)",
    "year": 2021,
    "artist_name": "Ludov",
    "artist_genre": "Indie",
    "youtube_link": "https://www.youtube.com/watch?v=PweyXXYvS6o",
    "imvdb_url": null,
    "source": "YouTube"
  },
  {
    "id": "yt_78lgKae6CbU",
    "song_title": "Ludovico Technique - Becoming Numb (Official Music Video)",
    "year": 2021,
    "artist_name": "Ludov",
    "artist_genre": "Indie",
    "youtube_link": "https://www.youtube.com/watch?v=78lgKae6CbU",
    "imvdb_url": null,
    "source": "YouTube"
  },
  {
    "id": "yt_H9pbohMqmwU",
    "song_title": "Mamonas Assassinas- Robocop Gay (Ao vivo no Faustão) HD",
    "year": 2021,
    "artist_name": "Mamonas Assassinas",
    "artist_genre": "Rock",
    "youtube_link": "https://www.youtube.com/watch?v=H9pbohMqmwU",
    "imvdb_url": null,
    "source": "YouTube"
  },
  {
    "id": "yt_r7Ib0r983DE",
    "song_title": "Maria Do Relento - Ritmo de Festa",
    "year": 2021,
    "artist_name": "Maria do Relento",
    "artist_genre": "Rock",
    "youtube_link": "https://www.youtube.com/watch?v=r7Ib0r983DE",
    "imvdb_url": null,
    "source": "YouTube"
  },
  {
    "id": "yt_jYK3avHqpak",
    "song_title": "[EXTRAORDINÁRIO] Andre Caldeira | Mediatriz | Barzinho em Casa MPB",
    "year": 2021,
    "artist_name": "Mediatriz",
    "artist_genre": "Rock",
    "youtube_link": "https://www.youtube.com/watch?v=jYK3avHqpak",
    "imvdb_url": null,
    "source": "YouTube"
  },
  {
    "id": "yt_TQa_eBjR4PA",
    "song_title": "Mestre Curica: Trilhas de Verão Virtual",
    "year": 2021,
    "artist_name": "Mestres da Guitarrada",
    "artist_genre": "Regional",
    "youtube_link": "https://www.youtube.com/watch?v=TQa_eBjR4PA",
    "imvdb_url": null,
    "source": "YouTube"
  },
  {
    "id": "yt_6fQc57t7VSA",
    "song_title": "Motörhead – Whorehouse Blues (Official Video)",
    "year": 2021,
    "artist_name": "Motir",
    "artist_genre": "Desconhecido",
    "youtube_link": "https://www.youtube.com/watch?v=6fQc57t7VSA",
    "imvdb_url": null,
    "source": "YouTube"
  },
  {
    "id": "yt_tHV7AwkzYWg",
    "song_title": "Motörhead – Rock Out (Official Video)",
    "year": 2021,
    "artist_name": "Motir",
    "artist_genre": "Desconhecido",
    "youtube_link": "https://www.youtube.com/watch?v=tHV7AwkzYWg",
    "imvdb_url": null,
    "source": "YouTube"
  },
  {
    "id": "yt_1_4ELAxKrDc",
    "song_title": "Tiësto & Ava Max - The Motto (Official Music Video)",
    "year": 2021,
    "artist_name": "Motir",
    "artist_genre": "Desconhecido",
    "youtube_link": "https://www.youtube.com/watch?v=1_4ELAxKrDc",
    "imvdb_url": null,
    "source": "YouTube"
  },
  {
    "id": "yt_oegTq8sYeKE",
    "song_title": "Mundo Livre S/A - LIVE na Ilha Grande 🦀",
    "year": 2021,
    "artist_name": "Mundo Livre S/A",
    "artist_genre": "Rock",
    "youtube_link": "https://www.youtube.com/watch?v=oegTq8sYeKE",
    "imvdb_url": null,
    "source": "YouTube"
  },
  {
    "id": "yt_xzHlY8YslnA",
    "song_title": "Pastor Epa - U mzuri sana Bwana | Lord, You are so good (Live) Official Gospel song 2021",
    "year": 2021,
    "artist_name": "Mzuri Sana",
    "artist_genre": "Rap",
    "youtube_link": "https://www.youtube.com/watch?v=xzHlY8YslnA",
    "imvdb_url": null,
    "source": "YouTube"
  },
  {
    "id": "yt_hFDbBujsRAs",
    "song_title": "Among Us Zombie Season 2 - Ep7 ~ 14 - Animation",
    "year": 2021,
    "artist_name": "Na\\'e7\\'e3o Zumbi",
    "artist_genre": "Desconhecido",
    "youtube_link": "https://www.youtube.com/watch?v=hFDbBujsRAs",
    "imvdb_url": null,
    "source": "YouTube"
  },
  {
    "id": "yt_mpoWMpj8jMk",
    "song_title": "Are the Ranger Zombies Now? | Dino Super Charge | Ninja Steel | Mini Movie | Action | Power Rangers",
    "year": 2021,
    "artist_name": "Na\\'e7\\'e3o Zumbi",
    "artist_genre": "Desconhecido",
    "youtube_link": "https://www.youtube.com/watch?v=mpoWMpj8jMk",
    "imvdb_url": null,
    "source": "YouTube"
  },
  {
    "id": "yt_T2Dp4Up9htc",
    "song_title": "Natiruts, Macaco - Rosas (Video Oficial)",
    "year": 2021,
    "artist_name": "Natiruts",
    "artist_genre": "Reggae",
    "youtube_link": "https://www.youtube.com/watch?v=T2Dp4Up9htc",
    "imvdb_url": null,
    "source": "YouTube"
  },
  {
    "id": "yt_deBz58UAsRs",
    "song_title": "Ana Castela - Nois é da Roça Bebê",
    "year": 2021,
    "artist_name": "Nenhum de N\\'f3s",
    "artist_genre": "Desconhecido",
    "youtube_link": "https://www.youtube.com/watch?v=deBz58UAsRs",
    "imvdb_url": null,
    "source": "YouTube"
  },
  {
    "id": "yt_wdCHlJoAP8I",
    "song_title": "Herman's Hermits - No Milk Today (1966)",
    "year": 2021,
    "artist_name": "No Milk Today",
    "artist_genre": "Punk",
    "youtube_link": "https://www.youtube.com/watch?v=wdCHlJoAP8I",
    "imvdb_url": null,
    "source": "YouTube"
  },
  {
    "id": "yt_3Hx7Bz6LGS0",
    "song_title": "Novos Baianos 🇧🇷 Preta, pretinha (1973) English Subtitles",
    "year": 2021,
    "artist_name": "Novos Baianos",
    "artist_genre": "MPB",
    "youtube_link": "https://www.youtube.com/watch?v=3Hx7Bz6LGS0",
    "imvdb_url": null,
    "source": "YouTube"
  },
  {
    "id": "yt_blR_Y28qnok",
    "song_title": "Tudo o que trai o teu coração - Novo Som & PG ( Clipe Oficial)",
    "year": 2021,
    "artist_name": "Novo Som",
    "artist_genre": "Pop",
    "youtube_link": "https://www.youtube.com/watch?v=blR_Y28qnok",
    "imvdb_url": null,
    "source": "YouTube"
  },
  {
    "id": "yt_-1R0Eln554g",
    "song_title": "O SURTO - A CERA (me pirou o cabeção) vídeo clipe - CARLA DIAZ E  LEONARDO BITTENCOURT ...",
    "year": 2021,
    "artist_name": "O Surto",
    "artist_genre": "Rock",
    "youtube_link": "https://www.youtube.com/watch?v=-1R0Eln554g",
    "imvdb_url": null,
    "source": "YouTube"
  },
  {
    "id": "yt_RvRjL017oUo",
    "song_title": "Jerusalema Feat Olodum Remix",
    "year": 2021,
    "artist_name": "Olodum",
    "artist_genre": "Axé",
    "youtube_link": "https://www.youtube.com/watch?v=RvRjL017oUo",
    "imvdb_url": null,
    "source": "YouTube"
  },
  {
    "id": "yt_mf2O5o3CeWc",
    "song_title": "Olodum - Faraó Divindade do Egito / Ensaio 1993",
    "year": 2021,
    "artist_name": "Olodum",
    "artist_genre": "Axé",
    "youtube_link": "https://www.youtube.com/watch?v=mf2O5o3CeWc",
    "imvdb_url": null,
    "source": "YouTube"
  },
  {
    "id": "yt_9QnWJhPF6OU",
    "song_title": "Andre de Brito - Queen of Spades (Official Video)",
    "year": 2021,
    "artist_name": "Os Britos",
    "artist_genre": "Rock",
    "youtube_link": "https://www.youtube.com/watch?v=9QnWJhPF6OU",
    "imvdb_url": null,
    "source": "YouTube"
  },
  {
    "id": "yt_2uOeoBKrNgU",
    "song_title": "Os Pata de Elefante feat - Phantom DK - Boom Fyahh | IDM Produções Oficial 2021",
    "year": 2021,
    "artist_name": "Pata de Elefante",
    "artist_genre": "Rock",
    "youtube_link": "https://www.youtube.com/watch?v=2uOeoBKrNgU",
    "imvdb_url": null,
    "source": "YouTube"
  },
  {
    "id": "yt_EOuuaOxlmFI",
    "song_title": "OS PATA DE ELEFANTE - A MANADA ft. ZOIO 3D, PRETA BEA, SUPER BIRO, FLA NEVES E DJ NANDEZ [BOOM BAP]",
    "year": 2021,
    "artist_name": "Pata de Elefante",
    "artist_genre": "Rock",
    "youtube_link": "https://www.youtube.com/watch?v=EOuuaOxlmFI",
    "imvdb_url": null,
    "source": "YouTube"
  },
  {
    "id": "yt_2ffZMMl52c4",
    "song_title": "Os Pata de Elefante - Mantendo o Peso Ft. D-DOg Mc (ClipOficial)",
    "year": 2021,
    "artist_name": "Pata de Elefante",
    "artist_genre": "Rock",
    "youtube_link": "https://www.youtube.com/watch?v=2ffZMMl52c4",
    "imvdb_url": null,
    "source": "YouTube"
  },
  {
    "id": "yt_PAvPfPtlLuM",
    "song_title": "PHOLHAS - MY MISTAKE - Legendado",
    "year": 2021,
    "artist_name": "Pholhas",
    "artist_genre": "Rock",
    "youtube_link": "https://www.youtube.com/watch?v=PAvPfPtlLuM",
    "imvdb_url": null,
    "source": "YouTube"
  },
  {
    "id": "yt_EgsBzmqTYs0",
    "song_title": "Helio Santisteban (PHOLHAS) - She made me cry",
    "year": 2021,
    "artist_name": "Pholhas",
    "artist_genre": "Rock",
    "youtube_link": "https://www.youtube.com/watch?v=EgsBzmqTYs0",
    "imvdb_url": null,
    "source": "YouTube"
  },
  {
    "id": "yt__2n_ajSh_uo",
    "song_title": "Jx.Zero - Playboy (Official Music Video)",
    "year": 2021,
    "artist_name": "The Playboys",
    "artist_genre": "Rock",
    "youtube_link": "https://www.youtube.com/watch?v=_2n_ajSh_uo",
    "imvdb_url": null,
    "source": "YouTube"
  },
  {
    "id": "yt_zig6qByF9bg",
    "song_title": "Tory Lanez Livestream • PLAYBOY Live",
    "year": 2021,
    "artist_name": "The Playboys",
    "artist_genre": "Rock",
    "youtube_link": "https://www.youtube.com/watch?v=zig6qByF9bg",
    "imvdb_url": null,
    "source": "YouTube"
  },
  {
    "id": "yt_6pbreU5ChmA",
    "song_title": "Cat TV ~ Mice in The Jerry Mouse Hole 🐭 8 HOURS 🐭 Videos for Cats",
    "year": 2021,
    "artist_name": "Ratos de Por\\'e3o",
    "artist_genre": "Desconhecido",
    "youtube_link": "https://www.youtube.com/watch?v=6pbreU5ChmA",
    "imvdb_url": null,
    "source": "YouTube"
  },
  {
    "id": "yt_SPmd4TwRM4g",
    "song_title": "Rebelde (Video Oficial)",
    "year": 2021,
    "artist_name": "Rebeldes",
    "artist_genre": "Pop",
    "youtube_link": "https://www.youtube.com/watch?v=SPmd4TwRM4g",
    "imvdb_url": null,
    "source": "YouTube"
  },
  {
    "id": "yt_6HNx41pJw1I",
    "song_title": "Os Replicantes | Bergamotas | Videoclipe Oficial",
    "year": 2021,
    "artist_name": "Os Replicantes",
    "artist_genre": "Punk",
    "youtube_link": "https://www.youtube.com/watch?v=6HNx41pJw1I",
    "imvdb_url": null,
    "source": "YouTube"
  },
  {
    "id": "yt_DmAOBosGlHY",
    "song_title": "Yusuf / Cat Stevens – Morning Has Broken (Official Lyric Video)",
    "year": 2021,
    "artist_name": "Stevens",
    "artist_genre": "Pop Rock",
    "youtube_link": "https://www.youtube.com/watch?v=DmAOBosGlHY",
    "imvdb_url": null,
    "source": "YouTube"
  },
  {
    "id": "yt_Txhq-9g1v9A",
    "song_title": "Tchê Garotos -  Pimentinha - DVD Ao Vivo e Bem Vivo",
    "year": 2021,
    "artist_name": "Tch Garotos",
    "artist_genre": "Desconhecido",
    "youtube_link": "https://www.youtube.com/watch?v=Txhq-9g1v9A",
    "imvdb_url": null,
    "source": "YouTube"
  },
  {
    "id": "yt__DF9gGMmtFE",
    "song_title": "Stiff Little Fingers - Alternative Ulster (Live At Rockpalast 1980)",
    "year": 2021,
    "artist_name": "Ulster",
    "artist_genre": "Punk",
    "youtube_link": "https://www.youtube.com/watch?v=_DF9gGMmtFE",
    "imvdb_url": null,
    "source": "YouTube"
  },
  {
    "id": "yt_y_jJlsIXAfs",
    "song_title": "stiff little fingers - alternative ulster (music video)",
    "year": 2021,
    "artist_name": "Ulster",
    "artist_genre": "Punk",
    "youtube_link": "https://www.youtube.com/watch?v=y_jJlsIXAfs",
    "imvdb_url": null,
    "source": "YouTube"
  },
  {
    "id": "yt_aDdOnl0bHO4",
    "song_title": "Joan Osborne - One Of Us",
    "year": 2021,
    "artist_name": "Uno de Deus",
    "artist_genre": "Gospel",
    "youtube_link": "https://www.youtube.com/watch?v=aDdOnl0bHO4",
    "imvdb_url": null,
    "source": "YouTube"
  },
  {
    "id": "yt_urXWl4DSFfw",
    "song_title": "Eliane Fernandes - Se Não Fosse Deus | Feat Luana Rodrigues (Clipe Oficial)",
    "year": 2021,
    "artist_name": "Uno de Deus",
    "artist_genre": "Gospel",
    "youtube_link": "https://www.youtube.com/watch?v=urXWl4DSFfw",
    "imvdb_url": null,
    "source": "YouTube"
  },
  {
    "id": "yt_y81yIo1_3o8",
    "song_title": "CeCe Winans: Goodness of God (Live)",
    "year": 2021,
    "artist_name": "Uno de Deus",
    "artist_genre": "Gospel",
    "youtube_link": "https://www.youtube.com/watch?v=y81yIo1_3o8",
    "imvdb_url": null,
    "source": "YouTube"
  },
  {
    "id": "yt_Lyj447vXU6g",
    "song_title": "Rogue - Viper (OFFICIAL MUSIC VIDEO)",
    "year": 2021,
    "artist_name": "Viper",
    "artist_genre": "Metal",
    "youtube_link": "https://www.youtube.com/watch?v=Lyj447vXU6g",
    "imvdb_url": null,
    "source": "YouTube"
  },
  {
    "id": "yt_jBeYe_uoJ2c",
    "song_title": "Viper - You'll Cowards Don't Even Smoke Crack '18 (Official Video)",
    "year": 2021,
    "artist_name": "Viper",
    "artist_genre": "Metal",
    "youtube_link": "https://www.youtube.com/watch?v=jBeYe_uoJ2c",
    "imvdb_url": null,
    "source": "YouTube"
  },
  {
    "id": "yt_NTVgAHxyeSI",
    "song_title": "Shaman's Harvest - \"Voices\" (Official Music Video)",
    "year": 2021,
    "artist_name": "Voices",
    "artist_genre": "Gospel",
    "youtube_link": "https://www.youtube.com/watch?v=NTVgAHxyeSI",
    "imvdb_url": null,
    "source": "YouTube"
  },
  {
    "id": "yt_RSbCDINX9N8",
    "song_title": "WRY - Where I Stand (Official Video)",
    "year": 2021,
    "artist_name": "Wry",
    "artist_genre": "Indie",
    "youtube_link": "https://www.youtube.com/watch?v=RSbCDINX9N8",
    "imvdb_url": null,
    "source": "YouTube"
  },
  {
    "id": "yt_UGE8Eiy5yp0",
    "song_title": "All Weapons & Power-Ups in Metal Slug History",
    "year": 2021,
    "artist_name": "Zumbis do Espa\\'e7o",
    "artist_genre": "Desconhecido",
    "youtube_link": "https://www.youtube.com/watch?v=UGE8Eiy5yp0",
    "imvdb_url": null,
    "source": "YouTube"
  },
  {
    "id": "yt_22gCVzU9WUY",
    "song_title": "Caetano Veloso - Anjos Tronchos (Clipe Oficial)",
    "year": 2021,
    "artist_name": "Caetano Veloso",
    "artist_genre": "Desconhecido",
    "youtube_link": "https://www.youtube.com/watch?v=22gCVzU9WUY",
    "imvdb_url": null,
    "source": "YouTube"
  },
  {
    "id": "yt_nWmJvqc_0BA",
    "song_title": "Como é Grande o Meu Amor por Você - Elas Cantam Roberto Carlos (Ao Vivo)",
    "year": 2021,
    "artist_name": "Roberto Carlos",
    "artist_genre": "MPB",
    "youtube_link": "https://www.youtube.com/watch?v=nWmJvqc_0BA",
    "imvdb_url": null,
    "source": "YouTube"
  },
  {
    "id": "yt_CQFXc2YQKL4",
    "song_title": "Cartola - Tive Sim",
    "year": 2021,
    "artist_name": "Cartola",
    "artist_genre": "Samba",
    "youtube_link": "https://www.youtube.com/watch?v=CQFXc2YQKL4",
    "imvdb_url": null,
    "source": "YouTube"
  },
  {
    "id": "yt_CcCtKg6IYDY",
    "song_title": "Emicida - São Pixinguinha | A COLORS SHOW",
    "year": 2021,
    "artist_name": "Pixinguinha",
    "artist_genre": "Choro",
    "youtube_link": "https://www.youtube.com/watch?v=CcCtKg6IYDY",
    "imvdb_url": null,
    "source": "YouTube"
  },
  {
    "id": "yt_5Z0IEmi56zE",
    "song_title": "Marisa Monte e Paulinho da Viola - Carinhoso (Pixinguinha)",
    "year": 2021,
    "artist_name": "Pixinguinha",
    "artist_genre": "Choro",
    "youtube_link": "https://www.youtube.com/watch?v=5Z0IEmi56zE",
    "imvdb_url": null,
    "source": "YouTube"
  },
  {
    "id": "yt_0K8N_2FVoNQ",
    "song_title": "São Pixinguinha - A COLORS SHOW",
    "year": 2021,
    "artist_name": "Pixinguinha",
    "artist_genre": "Choro",
    "youtube_link": "https://www.youtube.com/watch?v=0K8N_2FVoNQ",
    "imvdb_url": null,
    "source": "YouTube"
  },
  {
    "id": "yt_I4XBs99nQCc",
    "song_title": "Chico Science & Nação Zumbi - Da Lama Ao Caos (Video clipe)",
    "year": 2021,
    "artist_name": "Chico Science",
    "artist_genre": "Rock",
    "youtube_link": "https://www.youtube.com/watch?v=I4XBs99nQCc",
    "imvdb_url": null,
    "source": "YouTube"
  },
  {
    "id": "yt_o-gkzqXzS4k",
    "song_title": "Chico Science & Nação Zumbi - Maracatu de Tiro Certeiro (Video clipe)",
    "year": 2021,
    "artist_name": "Chico Science",
    "artist_genre": "Rock",
    "youtube_link": "https://www.youtube.com/watch?v=o-gkzqXzS4k",
    "imvdb_url": null,
    "source": "YouTube"
  },
  {
    "id": "yt_lWh6py31Dmc",
    "song_title": "Tom Jobim, Vinícius de Moraes, Toquinho e Miúcha - Tarde em Itapuã",
    "year": 2021,
    "artist_name": "Vinicius de Moraes",
    "artist_genre": "MPB",
    "youtube_link": "https://www.youtube.com/watch?v=lWh6py31Dmc",
    "imvdb_url": null,
    "source": "YouTube"
  },
  {
    "id": "yt_2Xc-Yll4xc0",
    "song_title": "Raul Seixas - Gita (Videoclipe Oficial)",
    "year": 2021,
    "artist_name": "Raul Seixas",
    "artist_genre": "Rock",
    "youtube_link": "https://www.youtube.com/watch?v=2Xc-Yll4xc0",
    "imvdb_url": null,
    "source": "YouTube"
  },
  {
    "id": "yt_8fNVNHQ_4ZM",
    "song_title": "Raul Seixas - Eu Também Vou Reclamar (Videoclipe Oficial)",
    "year": 2021,
    "artist_name": "Raul Seixas",
    "artist_genre": "Rock",
    "youtube_link": "https://www.youtube.com/watch?v=8fNVNHQ_4ZM",
    "imvdb_url": null,
    "source": "YouTube"
  },
  {
    "id": "yt_OTFN-zCSLY4",
    "song_title": "Raul Seixas - Maluco Beleza (Videoclipe Oficial)",
    "year": 2021,
    "artist_name": "Raul Seixas",
    "artist_genre": "Rock",
    "youtube_link": "https://www.youtube.com/watch?v=OTFN-zCSLY4",
    "imvdb_url": null,
    "source": "YouTube"
  },
  {
    "id": "yt_hu_XSw4e9GU",
    "song_title": "Raul Seixas - Tente Outra Vez (Videoclipe Oficial)",
    "year": 2021,
    "artist_name": "Raul Seixas",
    "artist_genre": "Rock",
    "youtube_link": "https://www.youtube.com/watch?v=hu_XSw4e9GU",
    "imvdb_url": null,
    "source": "YouTube"
  },
  {
    "id": "yt_CfgYcLBP9lI",
    "song_title": "Raul Seixas - Sociedade Alternativa (Videoclipe Oficial)",
    "year": 2021,
    "artist_name": "Raul Seixas",
    "artist_genre": "Rock",
    "youtube_link": "https://www.youtube.com/watch?v=CfgYcLBP9lI",
    "imvdb_url": null,
    "source": "YouTube"
  },
  {
    "id": "yt_693j3n2P3z0",
    "song_title": "Raul Seixas - O Trem das Sete (Videoclipe Oficial)",
    "year": 2021,
    "artist_name": "Raul Seixas",
    "artist_genre": "Rock",
    "youtube_link": "https://www.youtube.com/watch?v=693j3n2P3z0",
    "imvdb_url": null,
    "source": "YouTube"
  },
  {
    "id": "yt_DcoVEMethks",
    "song_title": "Raul Seixas - Eu Nasci Há Dez Mil Anos Atrás (Videoclipe Oficial)",
    "year": 2021,
    "artist_name": "Raul Seixas",
    "artist_genre": "Rock",
    "youtube_link": "https://www.youtube.com/watch?v=DcoVEMethks",
    "imvdb_url": null,
    "source": "YouTube"
  },
  {
    "id": "yt_Za0CHZ8Bd_Q",
    "song_title": "Villa Lobos plays Guitar - 1939 ( Part 1 )",
    "year": 2021,
    "artist_name": "Heitor Villa-Lobos",
    "artist_genre": "Clássico",
    "youtube_link": "https://www.youtube.com/watch?v=Za0CHZ8Bd_Q",
    "imvdb_url": null,
    "source": "YouTube"
  },
  {
    "id": "yt_O7WIwdnVdoA",
    "song_title": "Etude No. 1 • Villa-Lobos • Ana Vidović",
    "year": 2021,
    "artist_name": "Heitor Villa-Lobos",
    "artist_genre": "Clássico",
    "youtube_link": "https://www.youtube.com/watch?v=O7WIwdnVdoA",
    "imvdb_url": null,
    "source": "YouTube"
  },
  {
    "id": "yt_EMw4RyQ6wmU",
    "song_title": "Rose Moraes Ep. 6 - \"Isto é Meu Brasil\" written by Ary Barroso",
    "year": 2021,
    "artist_name": "Ary Barroso",
    "artist_genre": "Desconhecido",
    "youtube_link": "https://www.youtube.com/watch?v=EMw4RyQ6wmU",
    "imvdb_url": null,
    "source": "YouTube"
  },
  {
    "id": "yt_KkNjYIgHkvw",
    "song_title": "Hermeto Pascoal 🇧🇷 Música da Lagoa (1985) HQ 1080p",
    "year": 2021,
    "artist_name": "Hermeto Pascoal",
    "artist_genre": "Jazz",
    "youtube_link": "https://www.youtube.com/watch?v=KkNjYIgHkvw",
    "imvdb_url": null,
    "source": "YouTube"
  }
]