[
  {
    "id": "yt_VGzAk9LhH6w",
    "song_title": "Entre O Desespero E A Esperança",
    "year": 2007,
    "artist_name": "Ao Cubo",
    "artist_genre": "Rap",
    "youtube_link": "https://www.youtube.com/watch?v=VGzAk9LhH6w",
    "imvdb_url": null,
    "source": "YouTube"
  },
  {
    "id": "yt_l9MAEaxYBDc",
    "song_title": "Não Tem Lua",
    "year": 2006,
    "artist_name": "Asa de guia",
    "artist_genre": "Pop",
    "youtube_link": "https://www.youtube.com/watch?v=l9MAEaxYBDc",
    "imvdb_url": null,
    "source": "YouTube"
  },
  {
    "id": "yt_j1_zee9uHmM",
    "song_title": "Ela é Carioca",
    "year": 2007,
    "artist_name": "Os Cariocas",
    "artist_genre": "MPB",
    "youtube_link": "https://www.youtube.com/watch?v=j1_zee9uHmM",
    "imvdb_url": null,
    "source": "YouTube"
  },
  {
    "id": "yt_5O3KKlFZ1sU",
    "song_title": "Rio",
    "year": 2007,
    "artist_name": "Os Cariocas",
    "artist_genre": "MPB",
    "youtube_link": "https://www.youtube.com/watch?v=5O3KKlFZ1sU",
    "imvdb_url": null,
    "source": "YouTube"
  },
  {
    "id": "yt_Jj_GWA3t6qU",
    "song_title": "Berimbau e Wave",
    "year": 1989,
    "artist_name": "Os Cariocas",
    "artist_genre": "MPB",
    "youtube_link": "https://www.youtube.com/watch?v=Jj_GWA3t6qU",
    "imvdb_url": null,
    "source": "YouTube"
  },
  {
    "id": "yt_6B1Vc_UPmXk",
    "song_title": "Todo Azul Do Mar (Ao Vivo)",
    "year": 2007,
    "artist_name": "14 Bis",
    "artist_genre": "MPB",
    "youtube_link": "https://www.youtube.com/watch?v=6B1Vc_UPmXk",
    "imvdb_url": null,
    "source": "YouTube"
  },
  {
    "id": "yt_ZZMmbi1kfUo",
    "song_title": "Linda Juventude (Ao Vivo)",
    "year": 2007,
    "artist_name": "14 Bis",
    "artist_genre": "MPB",
    "youtube_link": "https://www.youtube.com/watch?v=ZZMmbi1kfUo",
    "imvdb_url": null,
    "source": "YouTube"
  },
  {
    "id": "yt_f5ONpooy7hs",
    "song_title": "Sonhando O Futuro (Ao Vivo)",
    "year": 2007,
    "artist_name": "14 Bis",
    "artist_genre": "MPB",
    "youtube_link": "https://www.youtube.com/watch?v=f5ONpooy7hs",
    "imvdb_url": null,
    "source": "YouTube"
  },
  {
    "id": "yt_Uqvqc2o38tw",
    "song_title": "Planeta Sonho (Ao Vivo)",
    "year": 2007,
    "artist_name": "14 Bis",
    "artist_genre": "MPB",
    "youtube_link": "https://www.youtube.com/watch?v=Uqvqc2o38tw",
    "imvdb_url": null,
    "source": "YouTube"
  },
  {
    "id": "yt_cyDHa1o4mvs",
    "song_title": "Mesmo De Brincadeira (Ao Vivo)",
    "year": 2007,
    "artist_name": "14 Bis",
    "artist_genre": "MPB",
    "youtube_link": "https://www.youtube.com/watch?v=cyDHa1o4mvs",
    "imvdb_url": null,
    "source": "YouTube"
  },
  {
    "id": "yt_OUs-0m4pTAI",
    "song_title": "Infinita Highway",
    "year": 1989,
    "artist_name": "Engenheiros do Hawaii",
    "artist_genre": "Rock",
    "youtube_link": "https://www.youtube.com/watch?v=2cTmeXesGM0",
    "imvdb_url": null,
    "source": "YouTube"
  },
  {
    "id": "yt_dU7z892mV8w",
    "song_title": "Sabe O Que Acontece Comigo",
    "year": 1984,
    "artist_name": "Garotos da Rua",
    "artist_genre": "Rock",
    "youtube_link": "https://www.youtube.com/watch?v=dU7z892mV8w",
    "imvdb_url": null,
    "source": "YouTube"
  },
  {
    "id": "yt_lkqcWKuzlQw",
    "song_title": "Balada Do Louco (Ao Vivo)",
    "year": 2006,
    "artist_name": "Os Mutantes",
    "artist_genre": "Rock",
    "youtube_link": "https://www.youtube.com/watch?v=lkqcWKuzlQw",
    "imvdb_url": null,
    "source": "YouTube"
  },
  {
    "id": "yt_bmoHC-FgwKs",
    "song_title": "I Feel A Little Spaced Out (Ando Meio Desligado) (Ao Vivo)",
    "year": 2006,
    "artist_name": "Os Mutantes",
    "artist_genre": "Rock",
    "youtube_link": "https://www.youtube.com/watch?v=bmoHC-FgwKs",
    "imvdb_url": null,
    "source": "YouTube"
  },
  {
    "id": "yt_TlYxS9kQljs",
    "song_title": "A Minha Menina (Ao Vivo)",
    "year": 2006,
    "artist_name": "Os Mutantes",
    "artist_genre": "Rock",
    "youtube_link": "https://www.youtube.com/watch?v=TlYxS9kQljs",
    "imvdb_url": null,
    "source": "YouTube"
  },
  {
    "id": "yt_dX5G812V5yI",
    "song_title": "Chuva Agora (Ao Vivo no VMB)",
    "year": 2008,
    "artist_name": "Nove Mil Anjos",
    "artist_genre": "Rock",
    "youtube_link": "https://www.youtube.com/watch?v=dX5G812V5yI",
    "imvdb_url": null,
    "source": "YouTube"
  },
  {
    "id": "yt_zggjYeV7aVA",
    "song_title": "Nicotina",
    "year": 1985,
    "artist_name": "Os Replicantes",
    "artist_genre": "Punk",
    "youtube_link": "https://www.youtube.com/watch?v=zggjYeV7aVA",
    "imvdb_url": null,
    "source": "YouTube"
  },
  {
    "id": "yt_DwVc0G3IKU4",
    "song_title": "Rosa de Hiroshima",
    "year": 1973,
    "artist_name": "Secos e Molhados",
    "artist_genre": "MPB",
    "youtube_link": "https://www.youtube.com/watch?v=DwVc0G3IKU4",
    "imvdb_url": null,
    "source": "YouTube"
  },
  {
    "id": "yt_jxRi0MS6j1k",
    "song_title": "Energia (Ao Vivo)",
    "year": 1982,
    "artist_name": "Jorge Ben Jor feat Lorraine com Tim Maia",
    "artist_genre": "MPB",
    "youtube_link": "https://www.youtube.com/watch?v=jxRi0MS6j1k",
    "imvdb_url": null,
    "source": "YouTube"
  }
]
